Workbook

Sheet How to Use
B1: BA Services – AI Prompt Library (CARE + G.E.T.) — v1.0
B2: Portable edition • 126 prompts across 42 L3 BA services and 6 roles • Organisation-neutral: no client names, sectors or jurisdiction-specific rules — adapt the worked examples to your own domain
B4: What's in this workbook
B5: Prompt Library | C5: One Master prompt per L3 BA service plus Deliverable prompts for key deliverables — 126 prompts across Business BA (8 services), Business/Tech BA (9), Technical BA (6), Agile BA (6), Lead BA (6) and Practice Lead (7). Copy the 'Full Prompt (copy-paste)' cell and replace [BRACKETED PLACEHOLDERS].
B6: Prompt Scores | C6: Every prompt scored against the 10-criterion quality scorecard, with deduction notes and live summary stats.
B7: Quality Scorecard | C7: The rubric itself (blank, ready to score any new prompt) with bands and the worked example.
B8: Delivery Contexts | C8: The 11 delivery contexts (system update, agile, transition, procurement, data warehouse, AI agentic, leadership...) mapped to the services and prompt IDs most used in each — start here if you know your project type but not which prompt you need.
B11: The CARE framework + G.E.T. validation
B12: C – Context | C12: Who am I, who is the audience, plus my organisation's constraints and the data-safety rule (de-identified or synthetic inputs only).
B13: A – Action | C13: One clear task with named inputs, plus 'ask me up to 5 clarifying questions first'.
B14: R – Result/Format | C14: Exact sections, tables and flags — checkable. Includes the no-invention rule: unverified = [TBC], proposed values = [PROPOSED — VALIDATE].
B15: E – Example | C15: A concrete sample the AI can imitate — every prompt has a hand-written one.
B16: G.E.T. | C16: Every prompt ends with Generate → Explain (break down the synthesis logic) → Test (list sources, cross-reference facts, list assumptions).
B18: Version history
B19: v0.1 → v0.2 | C19: First pass in CO-STAR (66 prompts, 22 services); reframed to CARE + G.E.T. per training feedback; quality scorecard added; all prompts scored (mean 18.1).
B20: v0.2 → v0.3 | C20: Extended to the 42-service L3 catalogue (+60 prompts for Strategic Advisory, Agile BA, Lead BA, Practice Lead); AI Transformation and Data & Reporting masters enriched; template hardened with in-prompt data-safety and no-invention rules (the two systematic deductions from the v0.2 scoring) — mean score now 19.7.
B21: v0.3 → v1.0 | C21: Portable edition. All organisation-specific content removed: employer identity, sector framing, named legislation and standards replaced with neutral equivalents, and every worked example rewritten in a generic case-management / service-request domain. Scores unchanged — the CARE structure, validation steps and level of concreteness are identical.
B22: Library statistics (live formulas)
B23: Total prompts | C23: =COUNTA('Prompt Library'!A2:A200) -> 126
B24: Master prompts | C24: =COUNTIF('Prompt Library'!E2:E200,"Master") -> 42
B25: Deliverable prompts | C25: =COUNTIF('Prompt Library'!E2:E200,"Deliverable") -> 84
B26: Services covered | C26: =SUMPRODUCT(('Prompt Library'!C2:C127<>"")/COUNTIF('Prompt Library'!C2:C127,'Prompt Library'!C2:C127&"")) -> 42
B27: Average quality score | C27: =ROUND(AVERAGE('Prompt Scores'!O2:O127),2) -> 19.67
B29: Adapting this library | C29: Two edits make the library organisation-specific again: (1) add your organisation and sector to the [PROJECT NAME AND ONE-LINE DESCRIPTION] placeholder or extend the # CONTEXT block; (2) replace the worked example in each # EXAMPLE block with one from your own domain — the example is what most shapes output quality. Name your privacy, security and residency obligations explicitly where the prompts refer to them generically.

Sheet Prompt Library
A1: ID | B1: Role | C1: BA Service | D1: Prompt Name | E1: Type | F1: Target Deliverable(s) | G1: C – Context | H1: A – Action | I1: R – Result/Format | J1: E – Example | K1: Validation (G.E.T.) | L1: Full Prompt (copy-paste)
A2: BB-01-M | B2: Business BA | C2: Benefits Realisation & KPI Management | D2: Master – Benefits Realisation & KPI Management | E2: Master | F2: Benefits Measures; KPI Reports; Value Realisation Assessments | G2: I am a business analyst (Business BA). I am working on [PROJECT NAME AND ONE-LINE DESCRIPTION]. My work must respect my organisation's privacy, information-security and data-residency obligations. Everything I paste is de-identified or synthetic — if any input appears to contain real personal or sensitive data, stop and alert me before proceeding. The initiative's stated benefits are: [LIST EXPECTED BENEFITS FROM THE BUSINESS CASE]. Current measurement baseline: [WHAT IS MEASURED TODAY, OR 'UNKNOWN']. The audience for this output: Benefit owners, the project sponsor and the PMO; summaries may be lifted into executive and board reporting. | H2: Act as my analysis partner for benefits realisation: define measurable benefits, design the KPIs and measures that evidence them, and assess whether value is actually being delivered, so the organisation can report outcomes credibly and identify optimisation opportunities. Produce, as I request them: (1) a benefits map linking initiative outputs to outcomes to benefits; (2) a KPI definition table (KPI, definition, formula, baseline, target, data source, frequency, owner); (3) a value realisation assessment comparing actuals to targets with root causes and optimisation recommendations. Before drafting, ask me up to 5 clarifying questions about anything missing, then wait for my answers. | I2: Structured, evidence-based business analysis writing aligned to BABOK good practice. Use clear headings, numbered requirements and tables where they aid scanning. Plain English; expand every acronym on first use; no marketing language. Every benefit must trace to a measurable KPI with a baseline, target, data source and owner. Keep the language professional, plain-English and appropriate for a business audience. Do not invent facts or figures: mark anything you could not verify from my inputs as [TBC] and any value you propose yourself as [PROPOSED — VALIDATE]. Treat the output as a first draft for my review, not a finished artefact. | J2: Example KPI row I expect: "KPI: Median case determination time | Definition: calendar days from case lodgement to final decision | Formula: median(decision_date − lodgement_date) | Baseline: 14.2 days (FY25) | Target: 10 days by Jun 2027 | Source: case management system | Frequency: monthly | Owner: Operations Manager". | K2: Generate: produce the output requested above. Explain: then break down, step by step, the logic you used to synthesise your answer — how you interpreted each of my inputs and why you structured the output the way you did. Test: list the source references you used for your analysis (my pasted inputs, earlier turns in this conversation, or your general knowledge — label which is which); cross-reference the key facts in your output against those sources and flag anything that does not trace back to a source; and list every additional assumption you made in your interpretation so I can verify or correct it. | L2: # CONTEXT I am a business analyst (Business BA). I am working on [PROJECT NAME AND ONE-LINE DESCRIPTION]. My work must respect my organisation's privacy, information-security and data-residency obligations. Everything I paste is de-identified or synthetic — if any input appears to contain real personal or sensitive data, stop and alert me before proceeding. The initiative's stated benefits are: [LIST EXPECTED BENEFITS FROM THE BUSINESS CASE]. Current measurement baseline: [WHAT IS MEASURED TODAY, OR 'UNKNOWN']. The audience for this output: Benefit owners, the project sponsor and the PMO; summaries may be lifted into executive and board reporting. # ACTION Act as my analysis partner for benefits realisation: define measurable benefits, design the KPIs and measures that evidence them, and assess whether value is actually being delivered, so the organisation can report outcomes credibly and identify optimisation opportunities. Produce, as I request them: (1) a benefits map linking initiative outputs to outcomes to benefits; (2) a KPI definition table (KPI, definition, formula, baseline, target, data source, frequency, owner); (3) a value realisation assessment comparing actuals to targets with root causes and optimisation recommendations. Before drafting, ask me up to 5 clarifying questions about anything missing, then wait for my answers. # RESULT / FORMAT Structured, evidence-based business analysis writing aligned to BABOK good practice. Use clear headings, numbered requirements and tables where they aid scanning. Plain English; expand every acronym on first use; no marketing language. Every benefit must trace to a measurable KPI with a baseline, target, data source and owner. Keep the language professional, plain-English and appropriate for a business audience. Do not invent facts or figures: mark anything you could not verify from my inputs as [TBC] and any value you propose yourself as [PROPOSED — VALIDATE]. Treat the output as a first draft for my review, not a finished artefact. # EXAMPLE Example KPI row I expect: "KPI: Median case determination time | Definition: calendar days from case lodgement to final decision | Formula: median(decision_date − lodgement_date) | Baseline: 14.2 days (FY25) | Target: 10 days by Jun 2027 | Source: case management system | Frequency: monthly | Owner: Operations Manager". # VALIDATION (GENERATE → EXPLAIN → TEST) Generate: produce the output requested above. Explain: then break down, step by step, the logic you used to synthesise your answer — how you interpreted each of my inputs and why you structured the output the way you did. Test: list the source references you used for your analysis (my pasted inputs, earlier turns in this conversation, or your general knowledge — label which is which); cross-reference the key facts in your output against those sources and flag anything that does not trace back to a source; and list every additional assumption you made in your interpretation so I can verify or correct it.
A3: BB-01-D1 | B3: Business BA | C3: Benefits Realisation & KPI Management | D3: KPI Definitions & Measures Table | E3: Deliverable | F3: Benefits Measures; KPI Definitions | G3: I am a business analyst (Business BA). I am working on [PROJECT NAME AND ONE-LINE DESCRIPTION]. My work must respect my organisation's privacy, information-security and data-residency obligations. Everything I paste is de-identified or synthetic — if any input appears to contain real personal or sensitive data, stop and alert me before proceeding. Benefits to be measured: [PASTE BENEFITS STATEMENTS OR BUSINESS CASE EXTRACT]. The audience for this output: Benefit owners and the reporting/data team who must build the measures. | H3: Turn the listed benefits into a rigorous KPI definition table that reporting teams could implement without further interpretation. Draft the table, then list measurement risks (gaming, lag, data quality) per KPI. Before drafting, ask me up to 5 clarifying questions about anything missing, then wait for my answers. | I3: One table, one row per KPI: KPI name; plain-English definition; calculation formula; unit; baseline; target and target date; data source system; collection frequency; accountable owner (role, not name). Flag any KPI that cannot currently be measured. Keep the language professional, plain-English and appropriate for a business audience. Do not invent facts or figures: mark anything you could not verify from my inputs as [TBC] and any value you propose yourself as [PROPOSED — VALIDATE]. Treat the output as a first draft for my review, not a finished artefact. | J3: Example row: "KPI: Cases resolved within 26 weeks | Definition: % of accepted cases closed within 26 weeks of lodgement | Formula: (cases closed ≤26wks ÷ accepted cases) × 100 | Baseline: [TO BE QUANTIFIED] | Target: +3pp on baseline | Source: case management system | Frequency: quarterly | Owner: Service Delivery Lead". | K3: Generate: produce the output requested above. Explain: then break down, step by step, the logic you used to synthesise your answer — how you interpreted each of my inputs and why you structured the output the way you did. Test: list the source references you used for your analysis (my pasted inputs, earlier turns in this conversation, or your general knowledge — label which is which); cross-reference the key facts in your output against those sources and flag anything that does not trace back to a source; and list every additional assumption you made in your interpretation so I can verify or correct it. | L3: # CONTEXT I am a business analyst (Business BA). I am working on [PROJECT NAME AND ONE-LINE DESCRIPTION]. My work must respect my organisation's privacy, information-security and data-residency obligations. Everything I paste is de-identified or synthetic — if any input appears to contain real personal or sensitive data, stop and alert me before proceeding. Benefits to be measured: [PASTE BENEFITS STATEMENTS OR BUSINESS CASE EXTRACT]. The audience for this output: Benefit owners and the reporting/data team who must build the measures. # ACTION Turn the listed benefits into a rigorous KPI definition table that reporting teams could implement without further interpretation. Draft the table, then list measurement risks (gaming, lag, data quality) per KPI. Before drafting, ask me up to 5 clarifying questions about anything missing, then wait for my answers. # RESULT / FORMAT One table, one row per KPI: KPI name; plain-English definition; calculation formula; unit; baseline; target and target date; data source system; collection frequency; accountable owner (role, not name). Flag any KPI that cannot currently be measured. Keep the language professional, plain-English and appropriate for a business audience. Do not invent facts or figures: mark anything you could not verify from my inputs as [TBC] and any value you propose yourself as [PROPOSED — VALIDATE]. Treat the output as a first draft for my review, not a finished artefact. # EXAMPLE Example row: "KPI: Cases resolved within 26 weeks | Definition: % of accepted cases closed within 26 weeks of lodgement | Formula: (cases closed ≤26wks ÷ accepted cases) × 100 | Baseline: [TO BE QUANTIFIED] | Target: +3pp on baseline | Source: case management system | Frequency: quarterly | Owner: Service Delivery Lead". # VALIDATION (GENERATE → EXPLAIN → TEST) Generate: produce the output requested above. Explain: then break down, step by step, the logic you used to synthesise your answer — how you interpreted each of my inputs and why you structured the output the way you did. Test: list the source references you used for your analysis (my pasted inputs, earlier turns in this conversation, or your general knowledge — label which is which); cross-reference the key facts in your output against those sources and flag anything that does not trace back to a source; and list every additional assumption you made in your interpretation so I can verify or correct it.
A4: BB-01-D2 | B4: Business BA | C4: Benefits Realisation & KPI Management | D4: Value Realisation Assessment | E4: Deliverable | F4: Value Realisation Assessments; KPI Reports | G4: I am a business analyst (Business BA). I am working on [PROJECT NAME AND ONE-LINE DESCRIPTION]. My work must respect my organisation's privacy, information-security and data-residency obligations. Everything I paste is de-identified or synthetic — if any input appears to contain real personal or sensitive data, stop and alert me before proceeding. Planned benefits and targets: [PASTE]. Actual results to date: [PASTE KPI ACTUALS / EXTRACT]. The audience for this output: Sponsor and steering committee. | H4: Assess realised value against plan, explain variances, and recommend optimisation actions. Draft the assessment (max 2 pages equivalent). Where data is insufficient to judge a benefit, say so explicitly rather than inferring success. Before drafting, ask me up to 5 clarifying questions about anything missing, then wait for my answers. | I4: Short report: RAG summary table per benefit; variance analysis; root causes distinguished from symptoms; prioritised recommendations with owner and effort estimate. Keep the language professional, plain-English and appropriate for a business audience. Do not invent facts or figures: mark anything you could not verify from my inputs as [TBC] and any value you propose yourself as [PROPOSED — VALIDATE]. Treat the output as a first draft for my review, not a finished artefact. | J4: Example variance line: "Benefit B2 – Reduced manual rework: AMBER. Target 30% reduction; actual 12%. Root cause: exception queue still routed to legacy team (process, not system). Recommendation: extend auto-routing rules to exception types 3–5; owner: Ops Improvement; effort: low." | K4: Generate: produce the output requested above. Explain: then break down, step by step, the logic you used to synthesise your answer — how you interpreted each of my inputs and why you structured the output the way you did. Test: list the source references you used for your analysis (my pasted inputs, earlier turns in this conversation, or your general knowledge — label which is which); cross-reference the key facts in your output against those sources and flag anything that does not trace back to a source; and list every additional assumption you made in your interpretation so I can verify or correct it. | L4: # CONTEXT I am a business analyst (Business BA). I am working on [PROJECT NAME AND ONE-LINE DESCRIPTION]. My work must respect my organisation's privacy, information-security and data-residency obligations. Everything I paste is de-identified or synthetic — if any input appears to contain real personal or sensitive data, stop and alert me before proceeding. Planned benefits and targets: [PASTE]. Actual results to date: [PASTE KPI ACTUALS / EXTRACT]. The audience for this output: Sponsor and steering committee. # ACTION Assess realised value against plan, explain variances, and recommend optimisation actions. Draft the assessment (max 2 pages equivalent). Where data is insufficient to judge a benefit, say so explicitly rather than inferring success. Before drafting, ask me up to 5 clarifying questions about anything missing, then wait for my answers. # RESULT / FORMAT Short report: RAG summary table per benefit; variance analysis; root causes distinguished from symptoms; prioritised recommendations with owner and effort estimate. Keep the language professional, plain-English and appropriate for a business audience. Do not invent facts or figures: mark anything you could not verify from my inputs as [TBC] and any value you propose yourself as [PROPOSED — VALIDATE]. Treat the output as a first draft for my review, not a finished artefact. # EXAMPLE Example variance line: "Benefit B2 – Reduced manual rework: AMBER. Target 30% reduction; actual 12%. Root cause: exception queue still routed to legacy team (process, not system). Recommendation: extend auto-routing rules to exception types 3–5; owner: Ops Improvement; effort: low." # VALIDATION (GENERATE → EXPLAIN → TEST) Generate: produce the output requested above. Explain: then break down, step by step, the logic you used to synthesise your answer — how you interpreted each of my inputs and why you structured the output the way you did. Test: list the source references you used for your analysis (my pasted inputs, earlier turns in this conversation, or your general knowledge — label which is which); cross-reference the key facts in your output against those sources and flag anything that does not trace back to a source; and list every additional assumption you made in your interpretation so I can verify or correct it.
A5: BB-02-M | B5: Business BA | C5: Business Needs Assessments (Initial and High Level Requirements) | D5: Master – Business Needs Assessment | E5: Master | F5: Discovery Notes; Workshop Outputs; Business Needs Statements | G5: I am a business analyst (Business BA). I am working on [PROJECT NAME AND ONE-LINE DESCRIPTION]. My work must respect my organisation's privacy, information-security and data-residency obligations. Everything I paste is de-identified or synthetic — if any input appears to contain real personal or sensitive data, stop and alert me before proceeding. Discovery stage: [NEW INITIATIVE / EXISTING PROBLEM]. What we know so far: [PASTE ANY BRIEFS, EMAILS OR NOTES]. The audience for this output: Business stakeholders and SMEs contributing needs; outputs feed the project brief and requirements backlog. | H5: Support end-to-end elicitation of business needs and high-level requirements: plan discovery sessions, generate strong questions, convert raw notes into structured needs statements, and expose conflicts and gaps between stakeholders. Support these modes on request: (1) workshop/interview plan with 8-12 questions sequenced broad-to-specific including conflict-testing questions; (2) structure raw notes into business needs statements ('The business needs the ability to [capability] so that [outcome]'); (3) simulate a named stakeholder so I can practise elicitation, then critique which questions I missed. Before drafting, ask me up to 5 clarifying questions about anything missing, then wait for my answers. | I5: Structured, evidence-based business analysis writing aligned to BABOK good practice. Use clear headings, numbered requirements and tables where they aid scanning. Plain English; expand every acronym on first use; no marketing language. Distinguish clearly between (a) explicit stakeholder statements, (b) implied needs, and (c) items needing clarification, with source attribution. Keep the language professional, plain-English and appropriate for a business audience. Do not invent facts or figures: mark anything you could not verify from my inputs as [TBC] and any value you propose yourself as [PROPOSED — VALIDATE]. Treat the output as a first draft for my review, not a finished artefact. | J5: Example needs statement I expect: "The business needs the ability to see all open actions for a customer across cases and enquiries in one view, so that staff do not request information the customer has already provided." | K5: Generate: produce the output requested above. Explain: then break down, step by step, the logic you used to synthesise your answer — how you interpreted each of my inputs and why you structured the output the way you did. Test: list the source references you used for your analysis (my pasted inputs, earlier turns in this conversation, or your general knowledge — label which is which); cross-reference the key facts in your output against those sources and flag anything that does not trace back to a source; and list every additional assumption you made in your interpretation so I can verify or correct it. | L5: # CONTEXT I am a business analyst (Business BA). I am working on [PROJECT NAME AND ONE-LINE DESCRIPTION]. My work must respect my organisation's privacy, information-security and data-residency obligations. Everything I paste is de-identified or synthetic — if any input appears to contain real personal or sensitive data, stop and alert me before proceeding. Discovery stage: [NEW INITIATIVE / EXISTING PROBLEM]. What we know so far: [PASTE ANY BRIEFS, EMAILS OR NOTES]. The audience for this output: Business stakeholders and SMEs contributing needs; outputs feed the project brief and requirements backlog. # ACTION Support end-to-end elicitation of business needs and high-level requirements: plan discovery sessions, generate strong questions, convert raw notes into structured needs statements, and expose conflicts and gaps between stakeholders. Support these modes on request: (1) workshop/interview plan with 8-12 questions sequenced broad-to-specific including conflict-testing questions; (2) structure raw notes into business needs statements ('The business needs the ability to [capability] so that [outcome]'); (3) simulate a named stakeholder so I can practise elicitation, then critique which questions I missed. Before drafting, ask me up to 5 clarifying questions about anything missing, then wait for my answers. # RESULT / FORMAT Structured, evidence-based business analysis writing aligned to BABOK good practice. Use clear headings, numbered requirements and tables where they aid scanning. Plain English; expand every acronym on first use; no marketing language. Distinguish clearly between (a) explicit stakeholder statements, (b) implied needs, and (c) items needing clarification, with source attribution. Keep the language professional, plain-English and appropriate for a business audience. Do not invent facts or figures: mark anything you could not verify from my inputs as [TBC] and any value you propose yourself as [PROPOSED — VALIDATE]. Treat the output as a first draft for my review, not a finished artefact. # EXAMPLE Example needs statement I expect: "The business needs the ability to see all open actions for a customer across cases and enquiries in one view, so that staff do not request information the customer has already provided." # VALIDATION (GENERATE → EXPLAIN → TEST) Generate: produce the output requested above. Explain: then break down, step by step, the logic you used to synthesise your answer — how you interpreted each of my inputs and why you structured the output the way you did. Test: list the source references you used for your analysis (my pasted inputs, earlier turns in this conversation, or your general knowledge — label which is which); cross-reference the key facts in your output against those sources and flag anything that does not trace back to a source; and list every additional assumption you made in your interpretation so I can verify or correct it.
A6: BB-02-D1 | B6: Business BA | C6: Business Needs Assessments (Initial and High Level Requirements) | D6: Discovery Workshop Plan & Question Set | E6: Deliverable | F6: Workshop Outputs | G6: I am a business analyst (Business BA). I am working on [PROJECT NAME AND ONE-LINE DESCRIPTION]. My work must respect my organisation's privacy, information-security and data-residency obligations. Everything I paste is de-identified or synthetic — if any input appears to contain real personal or sensitive data, stop and alert me before proceeding. Workshop topic: [TOPIC]. Attendees: [ROLES]. Duration: [LENGTH]. What we already know: [SUMMARY]. The audience for this output: Workshop attendees (agenda) and the facilitating BA (question set and rationale). | H6: Design a discovery workshop that elicits business needs efficiently and surfaces disagreement early. Draft agenda + questions, plus a 'facilitation risks' list (dominant voices, scope drift, sensitive topics such as team performance) with mitigations. Before drafting, ask me up to 5 clarifying questions about anything missing, then wait for my answers. | I6: Timed agenda table; then the question set grouped by theme, sequenced broad-to-specific, each with the rationale and expected output; include at least two questions designed to expose conflicting stakeholder assumptions. Keep the language professional, plain-English and appropriate for a business audience. Do not invent facts or figures: mark anything you could not verify from my inputs as [TBC] and any value you propose yourself as [PROPOSED — VALIDATE]. Treat the output as a first draft for my review, not a finished artefact. | J6: Example question with rationale: "'Walk me through the last time this process went wrong — what happened next?' (Rationale: elicits the real exception path and who is affected; expected output: failure modes for the as-is map.)" | K6: Generate: produce the output requested above. Explain: then break down, step by step, the logic you used to synthesise your answer — how you interpreted each of my inputs and why you structured the output the way you did. Test: list the source references you used for your analysis (my pasted inputs, earlier turns in this conversation, or your general knowledge — label which is which); cross-reference the key facts in your output against those sources and flag anything that does not trace back to a source; and list every additional assumption you made in your interpretation so I can verify or correct it. | L6: # CONTEXT I am a business analyst (Business BA). I am working on [PROJECT NAME AND ONE-LINE DESCRIPTION]. My work must respect my organisation's privacy, information-security and data-residency obligations. Everything I paste is de-identified or synthetic — if any input appears to contain real personal or sensitive data, stop and alert me before proceeding. Workshop topic: [TOPIC]. Attendees: [ROLES]. Duration: [LENGTH]. What we already know: [SUMMARY]. The audience for this output: Workshop attendees (agenda) and the facilitating BA (question set and rationale). # ACTION Design a discovery workshop that elicits business needs efficiently and surfaces disagreement early. Draft agenda + questions, plus a 'facilitation risks' list (dominant voices, scope drift, sensitive topics such as team performance) with mitigations. Before drafting, ask me up to 5 clarifying questions about anything missing, then wait for my answers. # RESULT / FORMAT Timed agenda table; then the question set grouped by theme, sequenced broad-to-specific, each with the rationale and expected output; include at least two questions designed to expose conflicting stakeholder assumptions. Keep the language professional, plain-English and appropriate for a business audience. Do not invent facts or figures: mark anything you could not verify from my inputs as [TBC] and any value you propose yourself as [PROPOSED — VALIDATE]. Treat the output as a first draft for my review, not a finished artefact. # EXAMPLE Example question with rationale: "'Walk me through the last time this process went wrong — what happened next?' (Rationale: elicits the real exception path and who is affected; expected output: failure modes for the as-is map.)" # VALIDATION (GENERATE → EXPLAIN → TEST) Generate: produce the output requested above. Explain: then break down, step by step, the logic you used to synthesise your answer — how you interpreted each of my inputs and why you structured the output the way you did. Test: list the source references you used for your analysis (my pasted inputs, earlier turns in this conversation, or your general knowledge — label which is which); cross-reference the key facts in your output against those sources and flag anything that does not trace back to a source; and list every additional assumption you made in your interpretation so I can verify or correct it.
A7: BB-02-D2 | B7: Business BA | C7: Business Needs Assessments (Initial and High Level Requirements) | D7: Raw Notes → Business Needs Statements | E7: Deliverable | F7: Business Needs Statements; Discovery Notes | G7: I am a business analyst (Business BA). I am working on [PROJECT NAME AND ONE-LINE DESCRIPTION]. My work must respect my organisation's privacy, information-security and data-residency obligations. Everything I paste is de-identified or synthetic — if any input appears to contain real personal or sensitive data, stop and alert me before proceeding. Raw material: [PASTE MEETING NOTES / TRANSCRIPT / EMAIL THREADS]. The audience for this output: Stakeholders who will validate the needs; the delivery team consuming them downstream. | H7: Convert the raw notes into clean, attributed business needs statements ready for validation. Draft the table. Do not invent needs that lack support in the notes — flag gaps instead. Before drafting, ask me up to 5 clarifying questions about anything missing, then wait for my answers. | I7: Table: ID; needs statement ('The business needs the ability to X so that Y'); type (explicit / implied / needs clarification); source (who said it / which note); suggested validation question. Separate section for decisions, actions and parking-lot items. Keep the language professional, plain-English and appropriate for a business audience. Do not invent facts or figures: mark anything you could not verify from my inputs as [TBC] and any value you propose yourself as [PROPOSED — VALIDATE]. Treat the output as a first draft for my review, not a finished artefact. | J7: Example row: "BN-04 | The business needs the ability to lodge service requests from a mobile device so that requests arrive within agreed timeframes | Type: explicit | Source: J. Chen, field ops workshop 12/7 | Validation question: does this extend to third parties without a registered account?" | K7: Generate: produce the output requested above. Explain: then break down, step by step, the logic you used to synthesise your answer — how you interpreted each of my inputs and why you structured the output the way you did. Test: list the source references you used for your analysis (my pasted inputs, earlier turns in this conversation, or your general knowledge — label which is which); cross-reference the key facts in your output against those sources and flag anything that does not trace back to a source; and list every additional assumption you made in your interpretation so I can verify or correct it. | L7: # CONTEXT I am a business analyst (Business BA). I am working on [PROJECT NAME AND ONE-LINE DESCRIPTION]. My work must respect my organisation's privacy, information-security and data-residency obligations. Everything I paste is de-identified or synthetic — if any input appears to contain real personal or sensitive data, stop and alert me before proceeding. Raw material: [PASTE MEETING NOTES / TRANSCRIPT / EMAIL THREADS]. The audience for this output: Stakeholders who will validate the needs; the delivery team consuming them downstream. # ACTION Convert the raw notes into clean, attributed business needs statements ready for validation. Draft the table. Do not invent needs that lack support in the notes — flag gaps instead. Before drafting, ask me up to 5 clarifying questions about anything missing, then wait for my answers. # RESULT / FORMAT Table: ID; needs statement ('The business needs the ability to X so that Y'); type (explicit / implied / needs clarification); source (who said it / which note); suggested validation question. Separate section for decisions, actions and parking-lot items. Keep the language professional, plain-English and appropriate for a business audience. Do not invent facts or figures: mark anything you could not verify from my inputs as [TBC] and any value you propose yourself as [PROPOSED — VALIDATE]. Treat the output as a first draft for my review, not a finished artefact. # EXAMPLE Example row: "BN-04 | The business needs the ability to lodge service requests from a mobile device so that requests arrive within agreed timeframes | Type: explicit | Source: J. Chen, field ops workshop 12/7 | Validation question: does this extend to third parties without a registered account?" # VALIDATION (GENERATE → EXPLAIN → TEST) Generate: produce the output requested above. Explain: then break down, step by step, the logic you used to synthesise your answer — how you interpreted each of my inputs and why you structured the output the way you did. Test: list the source references you used for your analysis (my pasted inputs, earlier turns in this conversation, or your general knowledge — label which is which); cross-reference the key facts in your output against those sources and flag anything that does not trace back to a source; and list every additional assumption you made in your interpretation so I can verify or correct it.
A8: BB-03-M | B8: Business BA | C8: Business Project Discovery & Problem Definition | D8: Master – Discovery & Problem Definition | E8: Master | F8: Problem Statements; Opportunity Assessments; Business Needs Statements; Business Case Inputs; Strategic Alignment Assessments; Risk Assessment Support | G8: I am a business analyst (Business BA). I am working on [PROJECT NAME AND ONE-LINE DESCRIPTION]. My work must respect my organisation's privacy, information-security and data-residency obligations. Everything I paste is de-identified or synthetic — if any input appears to contain real personal or sensitive data, stop and alert me before proceeding. Trigger for this work: [WHAT PROMPTED IT — incident, audit, strategy, pain point]. Known symptoms: [LIST]. Relevant organisational strategic objectives: [PASTE, OR 'NONE SUPPLIED']. The audience for this output: Sponsor, business case authors and investment governance forums. | H8: Help me define the real problem and the case for change: separate symptoms from root causes, quantify impact, frame the opportunity, test strategic alignment, and draft business case inputs and initial risk assessments. Produce on request: (1) a problem statement (situation, impact, magnitude, consequence of inaction); (2) an opportunity assessment with options at a high level; (3) strategic alignment assessment against the organisation's objectives; (4) an initial risk list (risk, cause, consequence, likelihood, impact, mitigation). Before drafting, ask me up to 5 clarifying questions about anything missing, then wait for my answers. | I8: Structured, evidence-based business analysis writing aligned to BABOK good practice. Use clear headings, numbered requirements and tables where they aid scanning. Plain English; expand every acronym on first use; no marketing language. Use the 5 Whys or fishbone technique for causes; every impact claim needs a number or an explicit '[TO BE QUANTIFIED]' flag. Keep the language professional, plain-English and appropriate for a business audience. Do not invent facts or figures: mark anything you could not verify from my inputs as [TBC] and any value you propose yourself as [PROPOSED — VALIDATE]. Treat the output as a first draft for my review, not a finished artefact. | J8: Example problem statement shape: "Customers submitting service requests by phone experience double handling: 40% of requests [TO BE QUANTIFIED] are re-keyed, adding ~3 days delay and creating transcription errors that flow into triage. If unaddressed, timeframe breaches will continue at roughly [X]/quarter." | K8: Generate: produce the output requested above. Explain: then break down, step by step, the logic you used to synthesise your answer — how you interpreted each of my inputs and why you structured the output the way you did. Test: list the source references you used for your analysis (my pasted inputs, earlier turns in this conversation, or your general knowledge — label which is which); cross-reference the key facts in your output against those sources and flag anything that does not trace back to a source; and list every additional assumption you made in your interpretation so I can verify or correct it. | L8: # CONTEXT I am a business analyst (Business BA). I am working on [PROJECT NAME AND ONE-LINE DESCRIPTION]. My work must respect my organisation's privacy, information-security and data-residency obligations. Everything I paste is de-identified or synthetic — if any input appears to contain real personal or sensitive data, stop and alert me before proceeding. Trigger for this work: [WHAT PROMPTED IT — incident, audit, strategy, pain point]. Known symptoms: [LIST]. Relevant organisational strategic objectives: [PASTE, OR 'NONE SUPPLIED']. The audience for this output: Sponsor, business case authors and investment governance forums. # ACTION Help me define the real problem and the case for change: separate symptoms from root causes, quantify impact, frame the opportunity, test strategic alignment, and draft business case inputs and initial risk assessments. Produce on request: (1) a problem statement (situation, impact, magnitude, consequence of inaction); (2) an opportunity assessment with options at a high level; (3) strategic alignment assessment against the organisation's objectives; (4) an initial risk list (risk, cause, consequence, likelihood, impact, mitigation). Before drafting, ask me up to 5 clarifying questions about anything missing, then wait for my answers. # RESULT / FORMAT Structured, evidence-based business analysis writing aligned to BABOK good practice. Use clear headings, numbered requirements and tables where they aid scanning. Plain English; expand every acronym on first use; no marketing language. Use the 5 Whys or fishbone technique for causes; every impact claim needs a number or an explicit '[TO BE QUANTIFIED]' flag. Keep the language professional, plain-English and appropriate for a business audience. Do not invent facts or figures: mark anything you could not verify from my inputs as [TBC] and any value you propose yourself as [PROPOSED — VALIDATE]. Treat the output as a first draft for my review, not a finished artefact. # EXAMPLE Example problem statement shape: "Customers submitting service requests by phone experience double handling: 40% of requests [TO BE QUANTIFIED] are re-keyed, adding ~3 days delay and creating transcription errors that flow into triage. If unaddressed, timeframe breaches will continue at roughly [X]/quarter." # VALIDATION (GENERATE → EXPLAIN → TEST) Generate: produce the output requested above. Explain: then break down, step by step, the logic you used to synthesise your answer — how you interpreted each of my inputs and why you structured the output the way you did. Test: list the source references you used for your analysis (my pasted inputs, earlier turns in this conversation, or your general knowledge — label which is which); cross-reference the key facts in your output against those sources and flag anything that does not trace back to a source; and list every additional assumption you made in your interpretation so I can verify or correct it.
A9: BB-03-D1 | B9: Business BA | C9: Business Project Discovery & Problem Definition | D9: Problem Statement & Opportunity Assessment | E9: Deliverable | F9: Problem Statements; Opportunity Assessments | G9: I am a business analyst (Business BA). I am working on [PROJECT NAME AND ONE-LINE DESCRIPTION]. My work must respect my organisation's privacy, information-security and data-residency obligations. Everything I paste is de-identified or synthetic — if any input appears to contain real personal or sensitive data, stop and alert me before proceeding. Symptoms and evidence gathered so far: [PASTE NOTES, DATA POINTS, COMPLAINTS, AUDIT FINDINGS]. The audience for this output: Sponsor and investment governance. | H9: Produce a sharp problem statement and opportunity assessment that would survive challenge at an investment committee. Apply 5 Whys to my symptoms first and show the chain, then draft both artefacts. Mark every unquantified impact '[TO BE QUANTIFIED]'. Before drafting, ask me up to 5 clarifying questions about anything missing, then wait for my answers. | I9: Problem statement in the format: current situation → who is affected and how often → measurable impact → consequence of doing nothing. Opportunity assessment: 3-4 response options (including 'do nothing') with indicative benefit, cost magnitude, and key risks each. Keep the language professional, plain-English and appropriate for a business audience. Do not invent facts or figures: mark anything you could not verify from my inputs as [TBC] and any value you propose yourself as [PROPOSED — VALIDATE]. Treat the output as a first draft for my review, not a finished artefact. | J9: Example option line: "Option 2 – Guided digital request form with save-and-resume: addresses re-keying at source; indicative benefit: removes ~80% of manual transcription; cost magnitude: medium (existing portal platform); key risk: digital exclusion of smaller customers — mitigation: retain assisted phone channel." | K9: Generate: produce the output requested above. Explain: then break down, step by step, the logic you used to synthesise your answer — how you interpreted each of my inputs and why you structured the output the way you did. Test: list the source references you used for your analysis (my pasted inputs, earlier turns in this conversation, or your general knowledge — label which is which); cross-reference the key facts in your output against those sources and flag anything that does not trace back to a source; and list every additional assumption you made in your interpretation so I can verify or correct it. | L9: # CONTEXT I am a business analyst (Business BA). I am working on [PROJECT NAME AND ONE-LINE DESCRIPTION]. My work must respect my organisation's privacy, information-security and data-residency obligations. Everything I paste is de-identified or synthetic — if any input appears to contain real personal or sensitive data, stop and alert me before proceeding. Symptoms and evidence gathered so far: [PASTE NOTES, DATA POINTS, COMPLAINTS, AUDIT FINDINGS]. The audience for this output: Sponsor and investment governance. # ACTION Produce a sharp problem statement and opportunity assessment that would survive challenge at an investment committee. Apply 5 Whys to my symptoms first and show the chain, then draft both artefacts. Mark every unquantified impact '[TO BE QUANTIFIED]'. Before drafting, ask me up to 5 clarifying questions about anything missing, then wait for my answers. # RESULT / FORMAT Problem statement in the format: current situation → who is affected and how often → measurable impact → consequence of doing nothing. Opportunity assessment: 3-4 response options (including 'do nothing') with indicative benefit, cost magnitude, and key risks each. Keep the language professional, plain-English and appropriate for a business audience. Do not invent facts or figures: mark anything you could not verify from my inputs as [TBC] and any value you propose yourself as [PROPOSED — VALIDATE]. Treat the output as a first draft for my review, not a finished artefact. # EXAMPLE Example option line: "Option 2 – Guided digital request form with save-and-resume: addresses re-keying at source; indicative benefit: removes ~80% of manual transcription; cost magnitude: medium (existing portal platform); key risk: digital exclusion of smaller customers — mitigation: retain assisted phone channel." # VALIDATION (GENERATE → EXPLAIN → TEST) Generate: produce the output requested above. Explain: then break down, step by step, the logic you used to synthesise your answer — how you interpreted each of my inputs and why you structured the output the way you did. Test: list the source references you used for your analysis (my pasted inputs, earlier turns in this conversation, or your general knowledge — label which is which); cross-reference the key facts in your output against those sources and flag anything that does not trace back to a source; and list every additional assumption you made in your interpretation so I can verify or correct it.
A10: BB-03-D2 | B10: Business BA | C10: Business Project Discovery & Problem Definition | D10: Business Case Inputs & Strategic Alignment | E10: Deliverable | F10: Business Case Inputs; Strategic Alignment Assessments | G10: I am a business analyst (Business BA). I am working on [PROJECT NAME AND ONE-LINE DESCRIPTION]. My work must respect my organisation's privacy, information-security and data-residency obligations. Everything I paste is de-identified or synthetic — if any input appears to contain real personal or sensitive data, stop and alert me before proceeding. Problem statement: [PASTE]. Preferred option(s): [PASTE]. Organisational strategic objectives: [PASTE]. The audience for this output: Business case author and finance reviewers. | H10: Draft the BA-owned inputs to the business case: benefits, costs categories, alignment narrative and assumptions. Draft the inputs. Never fabricate dollar figures — provide the structure and mark '[FINANCE TO ESTIMATE]'. Before drafting, ask me up to 5 clarifying questions about anything missing, then wait for my answers. | I10: Sections: benefits table (benefit, type: financial/non-financial, measure, timing); cost categories to be estimated (not invented figures); strategic alignment matrix (objective vs contribution with evidence); assumptions and constraints log. Keep the language professional, plain-English and appropriate for a business audience. Do not invent facts or figures: mark anything you could not verify from my inputs as [TBC] and any value you propose yourself as [PROPOSED — VALIDATE]. Treat the output as a first draft for my review, not a finished artefact. | J10: Example alignment row: "Objective: 'Better client experience' | Contribution: removes duplicate data requests to customers during case handling | Evidence: complaint theme #2 in FY25 voice-of-customer report [PASTE REF] | Strength: direct". | K10: Generate: produce the output requested above. Explain: then break down, step by step, the logic you used to synthesise your answer — how you interpreted each of my inputs and why you structured the output the way you did. Test: list the source references you used for your analysis (my pasted inputs, earlier turns in this conversation, or your general knowledge — label which is which); cross-reference the key facts in your output against those sources and flag anything that does not trace back to a source; and list every additional assumption you made in your interpretation so I can verify or correct it. | L10: # CONTEXT I am a business analyst (Business BA). I am working on [PROJECT NAME AND ONE-LINE DESCRIPTION]. My work must respect my organisation's privacy, information-security and data-residency obligations. Everything I paste is de-identified or synthetic — if any input appears to contain real personal or sensitive data, stop and alert me before proceeding. Problem statement: [PASTE]. Preferred option(s): [PASTE]. Organisational strategic objectives: [PASTE]. The audience for this output: Business case author and finance reviewers. # ACTION Draft the BA-owned inputs to the business case: benefits, costs categories, alignment narrative and assumptions. Draft the inputs. Never fabricate dollar figures — provide the structure and mark '[FINANCE TO ESTIMATE]'. Before drafting, ask me up to 5 clarifying questions about anything missing, then wait for my answers. # RESULT / FORMAT Sections: benefits table (benefit, type: financial/non-financial, measure, timing); cost categories to be estimated (not invented figures); strategic alignment matrix (objective vs contribution with evidence); assumptions and constraints log. Keep the language professional, plain-English and appropriate for a business audience. Do not invent facts or figures: mark anything you could not verify from my inputs as [TBC] and any value you propose yourself as [PROPOSED — VALIDATE]. Treat the output as a first draft for my review, not a finished artefact. # EXAMPLE Example alignment row: "Objective: 'Better client experience' | Contribution: removes duplicate data requests to customers during case handling | Evidence: complaint theme #2 in FY25 voice-of-customer report [PASTE REF] | Strength: direct". # VALIDATION (GENERATE → EXPLAIN → TEST) Generate: produce the output requested above. Explain: then break down, step by step, the logic you used to synthesise your answer — how you interpreted each of my inputs and why you structured the output the way you did. Test: list the source references you used for your analysis (my pasted inputs, earlier turns in this conversation, or your general knowledge — label which is which); cross-reference the key facts in your output against those sources and flag anything that does not trace back to a source; and list every additional assumption you made in your interpretation so I can verify or correct it.
A11: BB-04-M | B11: Business BA | C11: Data & Reporting Analysis | D11: Master – Data & Reporting Analysis | E11: Master | F11: Data Requirements; Data Mapping; Reporting Requirements; KPI Definitions | G11: I am a business analyst (Business BA). I am working on [PROJECT NAME AND ONE-LINE DESCRIPTION]. My work must respect my organisation's privacy, information-security and data-residency obligations. Everything I paste is de-identified or synthetic — if any input appears to contain real personal or sensitive data, stop and alert me before proceeding. Business area and decisions the data must support: [DESCRIBE]. Known source systems: [LIST, e.g. core case management system, billing system, request intake channel, data warehouse]. The audience for this output: Business data owners, reporting teams and the data engineering team. | H11: Define the business data, information and reporting requirements for this initiative: what data is needed, what it means, where it comes from, and what reports and KPIs it must feed. Produce on request: (1) data requirements catalogue (entity, element, business definition, classification incl. personal/health info, quality expectation); (2) source-to-target data mapping tables; (3) reporting requirements (report, purpose, audience, KPIs, dimensions, frequency, access restrictions); (4) KPI definitions; (5) for data warehouse / BI work: a business question catalogue (what/why/how/when/who per question), MECE validation of question themes, business logic and refresh-frequency definitions, and BI technical specification structure (sources, joins, logic — flagged for peer review via validation queries). Before drafting, ask me up to 5 clarifying questions about anything missing, then wait for my answers. | I11: Structured, evidence-based business analysis writing aligned to BABOK good practice. Use clear headings, numbered requirements and tables where they aid scanning. Plain English; expand every acronym on first use; no marketing language. Business language first; add technical detail (types, validation) only after meaning is agreed. Where the data includes personal or otherwise sensitive information, flag the classification per element. Keep the language professional, plain-English and appropriate for a business audience. Do not invent facts or figures: mark anything you could not verify from my inputs as [TBC] and any value you propose yourself as [PROPOSED — VALIDATE]. Treat the output as a first draft for my review, not a finished artefact. | J11: Example element row: "Entity: Request | Element: request_severity | Definition: initial severity band assigned at lodgement (1–4) per triage matrix | Classification: internal | Quality expectation: mandatory at creation, single value, revalidated at assessment". | K11: Generate: produce the output requested above. Explain: then break down, step by step, the logic you used to synthesise your answer — how you interpreted each of my inputs and why you structured the output the way you did. Test: list the source references you used for your analysis (my pasted inputs, earlier turns in this conversation, or your general knowledge — label which is which); cross-reference the key facts in your output against those sources and flag anything that does not trace back to a source; and list every additional assumption you made in your interpretation so I can verify or correct it. | L11: # CONTEXT I am a business analyst (Business BA). I am working on [PROJECT NAME AND ONE-LINE DESCRIPTION]. My work must respect my organisation's privacy, information-security and data-residency obligations. Everything I paste is de-identified or synthetic — if any input appears to contain real personal or sensitive data, stop and alert me before proceeding. Business area and decisions the data must support: [DESCRIBE]. Known source systems: [LIST, e.g. core case management system, billing system, request intake channel, data warehouse]. The audience for this output: Business data owners, reporting teams and the data engineering team. # ACTION Define the business data, information and reporting requirements for this initiative: what data is needed, what it means, where it comes from, and what reports and KPIs it must feed. Produce on request: (1) data requirements catalogue (entity, element, business definition, classification incl. personal/health info, quality expectation); (2) source-to-target data mapping tables; (3) reporting requirements (report, purpose, audience, KPIs, dimensions, frequency, access restrictions); (4) KPI definitions; (5) for data warehouse / BI work: a business question catalogue (what/why/how/when/who per question), MECE validation of question themes, business logic and refresh-frequency definitions, and BI technical specification structure (sources, joins, logic — flagged for peer review via validation queries). Before drafting, ask me up to 5 clarifying questions about anything missing, then wait for my answers. # RESULT / FORMAT Structured, evidence-based business analysis writing aligned to BABOK good practice. Use clear headings, numbered requirements and tables where they aid scanning. Plain English; expand every acronym on first use; no marketing language. Business language first; add technical detail (types, validation) only after meaning is agreed. Where the data includes personal or otherwise sensitive information, flag the classification per element. Keep the language professional, plain-English and appropriate for a business audience. Do not invent facts or figures: mark anything you could not verify from my inputs as [TBC] and any value you propose yourself as [PROPOSED — VALIDATE]. Treat the output as a first draft for my review, not a finished artefact. # EXAMPLE Example element row: "Entity: Request | Element: request_severity | Definition: initial severity band assigned at lodgement (1–4) per triage matrix | Classification: internal | Quality expectation: mandatory at creation, single value, revalidated at assessment". # VALIDATION (GENERATE → EXPLAIN → TEST) Generate: produce the output requested above. Explain: then break down, step by step, the logic you used to synthesise your answer — how you interpreted each of my inputs and why you structured the output the way you did. Test: list the source references you used for your analysis (my pasted inputs, earlier turns in this conversation, or your general knowledge — label which is which); cross-reference the key facts in your output against those sources and flag anything that does not trace back to a source; and list every additional assumption you made in your interpretation so I can verify or correct it.
A12: BB-04-D1 | B12: Business BA | C12: Data & Reporting Analysis | D12: Data Requirements & Dictionary | E12: Deliverable | F12: Data Requirements; Data Mapping | G12: I am a business analyst (Business BA). I am working on [PROJECT NAME AND ONE-LINE DESCRIPTION]. My work must respect my organisation's privacy, information-security and data-residency obligations. Everything I paste is de-identified or synthetic — if any input appears to contain real personal or sensitive data, stop and alert me before proceeding. Fields/entities in scope: [PASTE FIELD LIST, FORM, OR API EXTRACT]. Purpose of the data: [DESCRIBE]. The audience for this output: Data owners for validation; engineers for implementation. | H12: Produce a business data dictionary and requirements table for the fields in scope. Draft the dictionary, then list the top data-quality and privacy risks (e.g. health information exposure in reporting) with mitigations. Before drafting, ask me up to 5 clarifying questions about anything missing, then wait for my answers. | I12: Table: field name (standardised snake_case suggestion); business definition; data type; allowable values; validation rules; example value; data classification (public / internal / personal / health information); source system; quality rule. Flag ambiguous fields rather than guessing definitions. Keep the language professional, plain-English and appropriate for a business audience. Do not invent facts or figures: mark anything you could not verify from my inputs as [TBC] and any value you propose yourself as [PROPOSED — VALIDATE]. Treat the output as a first draft for my review, not a finished artefact. | J12: Example dictionary row: "Field: date_of_event | Definition: date the reported event occurred, as advised | Type: date (not future-dated) | Allowable: ≤ today | Validation: must be ≤ case lodgement date | Example: 2026-05-14 | Classification: personal | Source: request form Q3 | Quality rule: reject future dates at entry". | K12: Generate: produce the output requested above. Explain: then break down, step by step, the logic you used to synthesise your answer — how you interpreted each of my inputs and why you structured the output the way you did. Test: list the source references you used for your analysis (my pasted inputs, earlier turns in this conversation, or your general knowledge — label which is which); cross-reference the key facts in your output against those sources and flag anything that does not trace back to a source; and list every additional assumption you made in your interpretation so I can verify or correct it. | L12: # CONTEXT I am a business analyst (Business BA). I am working on [PROJECT NAME AND ONE-LINE DESCRIPTION]. My work must respect my organisation's privacy, information-security and data-residency obligations. Everything I paste is de-identified or synthetic — if any input appears to contain real personal or sensitive data, stop and alert me before proceeding. Fields/entities in scope: [PASTE FIELD LIST, FORM, OR API EXTRACT]. Purpose of the data: [DESCRIBE]. The audience for this output: Data owners for validation; engineers for implementation. # ACTION Produce a business data dictionary and requirements table for the fields in scope. Draft the dictionary, then list the top data-quality and privacy risks (e.g. health information exposure in reporting) with mitigations. Before drafting, ask me up to 5 clarifying questions about anything missing, then wait for my answers. # RESULT / FORMAT Table: field name (standardised snake_case suggestion); business definition; data type; allowable values; validation rules; example value; data classification (public / internal / personal / health information); source system; quality rule. Flag ambiguous fields rather than guessing definitions. Keep the language professional, plain-English and appropriate for a business audience. Do not invent facts or figures: mark anything you could not verify from my inputs as [TBC] and any value you propose yourself as [PROPOSED — VALIDATE]. Treat the output as a first draft for my review, not a finished artefact. # EXAMPLE Example dictionary row: "Field: date_of_event | Definition: date the reported event occurred, as advised | Type: date (not future-dated) | Allowable: ≤ today | Validation: must be ≤ case lodgement date | Example: 2026-05-14 | Classification: personal | Source: request form Q3 | Quality rule: reject future dates at entry". # VALIDATION (GENERATE → EXPLAIN → TEST) Generate: produce the output requested above. Explain: then break down, step by step, the logic you used to synthesise your answer — how you interpreted each of my inputs and why you structured the output the way you did. Test: list the source references you used for your analysis (my pasted inputs, earlier turns in this conversation, or your general knowledge — label which is which); cross-reference the key facts in your output against those sources and flag anything that does not trace back to a source; and list every additional assumption you made in your interpretation so I can verify or correct it.
... A127: PL-07-D2 | B127: Practice Lead | C127: Tooling & AI Enablement | D127: AI Adoption Guidelines & Guardrails (Practice) | E127: Deliverable | F127: Tooling Standards; AI Adoption Guidelines & Guardrails | G127: I am a BA practice lead. I am working on [PROJECT NAME AND ONE-LINE DESCRIPTION]. My work must respect my organisation's privacy, information-security and data-residency obligations. Everything I paste is de-identified or synthetic — if any input appears to contain real personal or sensitive data, stop and alert me before proceeding. Practice context: [PRACTICE SIZE, MIX OF PERMANENT/CONTRACT, DELIVERY PORTFOLIO SHAPE]. Approved AI tools: [LIST]. Organisational AI policy: [PASTE OR REFERENCE]. Known incidents/near-misses: [ANY]. The audience for this output: All practice BAs; endorsed by security/privacy and the sponsor. | H127: Draft the practice's AI adoption guidelines: what BAs may use AI for, what they must never do, and the validation discipline that makes outputs trustworthy. Draft the guidelines. Where my organisational policy is stricter than these defaults, follow the policy and note it; where it is silent, mark the gap for the policy owner. Before drafting, ask me up to 5 clarifying questions about anything missing, then wait for my answers. | I127: Guidelines: approved uses by task type (drafting, summarising, analysis support, test scenario generation — each with its guardrail); prohibited uses (decisions about individuals, unreviewed outputs into governance artefacts, real personal or sensitive data as input — de-identified or synthetic only); the validation duty (Generate→Explain→Test on every substantive output, human accountable always); prompt quality expectations (use the practice prompt library; new prompts scored on the 10-criterion scorecard before sharing); transparency rule (when to disclose AI assistance); escalation path for uncertainty. Aligned to my pasted policy with conflicts flagged for resolution. Keep the language professional, plain-English and appropriate for a business audience. Do not invent facts or figures: mark anything you could not verify from my inputs as [TBC] and any value you propose yourself as [PROPOSED — VALIDATE]. Treat the output as a first draft for my review, not a finished artefact. | J127: Example prohibited-use line: "Prohibited: entering real customer, employee or other identifying information, or sensitive personal information, into any AI tool — approved or not. Use de-identified or synthetic data. No AI-generated content enters a governance artefact without named-human review recorded." | K127: Generate: produce the output requested above. Explain: then break down, step by step, the logic you used to synthesise your answer — how you interpreted each of my inputs and why you structured the output the way you did. Test: list the source references you used for your analysis (my pasted inputs, earlier turns in this conversation, or your general knowledge — label which is which); cross-reference the key facts in your output against those sources and flag anything that does not trace back to a source; and list every additional assumption you made in your interpretation so I can verify or correct it. | L127: # CONTEXT I am a BA practice lead. I am working on [PROJECT NAME AND ONE-LINE DESCRIPTION]. My work must respect my organisation's privacy, information-security and data-residency obligations. Everything I paste is de-identified or synthetic — if any input appears to contain real personal or sensitive data, stop and alert me before proceeding. Practice context: [PRACTICE SIZE, MIX OF PERMANENT/CONTRACT, DELIVERY PORTFOLIO SHAPE]. Approved AI tools: [LIST]. Organisational AI policy: [PASTE OR REFERENCE]. Known incidents/near-misses: [ANY]. The audience for this output: All practice BAs; endorsed by security/privacy and the sponsor. # ACTION Draft the practice's AI adoption guidelines: what BAs may use AI for, what they must never do, and the validation discipline that makes outputs trustworthy. Draft the guidelines. Where my organisational policy is stricter than these defaults, follow the policy and note it; where it is silent, mark the gap for the policy owner. Before drafting, ask me up to 5 clarifying questions about anything missing, then wait for my answers. # RESULT / FORMAT Guidelines: approved uses by task type (drafting, summarising, analysis support, test scenario generation — each with its guardrail); prohibited uses (decisions about individuals, unreviewed outputs into governance artefacts, real personal or sensitive data as input — de-identified or synthetic only); the validation duty (Generate→Explain→Test on every substantive output, human accountable always); prompt quality expectations (use the practice prompt library; new prompts scored on the 10-criterion scorecard before sharing); transparency rule (when to disclose AI assistance); escalation path for uncertainty. Aligned to my pasted policy with conflicts flagged for resolution. Keep the language professional, plain-English and appropriate for a business audience. Do not invent facts or figures: mark anything you could not verify from my inputs as [TBC] and any value you propose yourself as [PROPOSED — VALIDATE]. Treat the output as a first draft for my review, not a finished artefact. # EXAMPLE Example prohibited-use line: "Prohibited: entering real customer, employee or other identifying information, or sensitive personal information, into any AI tool — approved or not. Use de-identified or synthetic data. No AI-generated content enters a governance artefact without named-human review recorded." # VALIDATION (GENERATE → EXPLAIN → TEST) Generate: produce the output requested above. Explain: then break down, step by step, the logic you used to synthesise your answer — how you interpreted each of my inputs and why you structured the output the way you did. Test: list the source references you used for your analysis (my pasted inputs, earlier turns in this conversation, or your general knowledge — label which is which); cross-reference the key facts in your output against those sources and flag anything that does not trace back to a source; and list every additional assumption you made in your interpretation so I can verify or correct it.

Sheet Prompt Scores
A1: ID | B1: Prompt Name | C1: Type | D1: Role | E1: C1 Context | F1: C2 Action | G1: C3 Result | H1: C4 Example | I1: C5 Explain | J1: C6 Test | K1: C7 Anti-fab | L1: C8 Data safety | M1: C9 Reuse | N1: C10 Right-sized | O1: Total /20 | P1: Verdict | Q1: Deductions & suggested fixes
A2: BB-01-M | B2: Master – Benefits Realisation & KPI Management | C2: Master | D2: Business BA | E2: 2 | F2: 1 | G2: 2 | H2: 2 | I2: 2 | J2: 2 | K2: 2 | L2: 2 | M2: 2 | N2: 2 | O2: =SUM(E2:N2) -> 19 | P2: =IF(O2>=17,"Library-ready",IF(O2>=12,"Refine first","Rework")) -> Library-ready | Q2: Action 1/2: a menu of modes, not one task — deliberate flexibility, but costs single-task clarity. Fix: for repeated use of one mode, use the matching Deliverable prompt instead.
A3: BB-01-D1 | B3: KPI Definitions & Measures Table | C3: Deliverable | D3: Business BA | E3: 2 | F3: 2 | G3: 2 | H3: 2 | I3: 2 | J3: 2 | K3: 2 | L3: 2 | M3: 2 | N3: 2 | O3: =SUM(E3:N3) -> 20 | P3: =IF(O3>=17,"Library-ready",IF(O3>=12,"Refine first","Rework")) -> Library-ready | Q3: No deductions.
A4: BB-01-D2 | B4: Value Realisation Assessment | C4: Deliverable | D4: Business BA | E4: 2 | F4: 2 | G4: 2 | H4: 2 | I4: 2 | J4: 2 | K4: 2 | L4: 2 | M4: 2 | N4: 2 | O4: =SUM(E4:N4) -> 20 | P4: =IF(O4>=17,"Library-ready",IF(O4>=12,"Refine first","Rework")) -> Library-ready | Q4: No deductions.
A5: BB-02-M | B5: Master – Business Needs Assessment | C5: Master | D5: Business BA | E5: 2 | F5: 1 | G5: 2 | H5: 2 | I5: 2 | J5: 2 | K5: 2 | L5: 2 | M5: 2 | N5: 2 | O5: =SUM(E5:N5) -> 19 | P5: =IF(O5>=17,"Library-ready",IF(O5>=12,"Refine first","Rework")) -> Library-ready | Q5: Action 1/2: a menu of modes, not one task — deliberate flexibility, but costs single-task clarity. Fix: for repeated use of one mode, use the matching Deliverable prompt instead.
A6: BB-02-D1 | B6: Discovery Workshop Plan & Question Set | C6: Deliverable | D6: Business BA | E6: 2 | F6: 2 | G6: 2 | H6: 2 | I6: 2 | J6: 2 | K6: 2 | L6: 2 | M6: 2 | N6: 2 | O6: =SUM(E6:N6) -> 20 | P6: =IF(O6>=17,"Library-ready",IF(O6>=12,"Refine first","Rework")) -> Library-ready | Q6: No deductions.
A7: BB-02-D2 | B7: Raw Notes → Business Needs Statements | C7: Deliverable | D7: Business BA | E7: 2 | F7: 2 | G7: 2 | H7: 2 | I7: 2 | J7: 2 | K7: 2 | L7: 2 | M7: 2 | N7: 2 | O7: =SUM(E7:N7) -> 20 | P7: =IF(O7>=17,"Library-ready",IF(O7>=12,"Refine first","Rework")) -> Library-ready | Q7: No deductions.
A8: BB-03-M | B8: Master – Discovery & Problem Definition | C8: Master | D8: Business BA | E8: 2 | F8: 1 | G8: 2 | H8: 2 | I8: 2 | J8: 2 | K8: 2 | L8: 2 | M8: 2 | N8: 2 | O8: =SUM(E8:N8) -> 19 | P8: =IF(O8>=17,"Library-ready",IF(O8>=12,"Refine first","Rework")) -> Library-ready | Q8: Action 1/2: a menu of modes, not one task — deliberate flexibility, but costs single-task clarity. Fix: for repeated use of one mode, use the matching Deliverable prompt instead.
A9: BB-03-D1 | B9: Problem Statement & Opportunity Assessment | C9: Deliverable | D9: Business BA | E9: 2 | F9: 2 | G9: 2 | H9: 2 | I9: 2 | J9: 2 | K9: 2 | L9: 2 | M9: 2 | N9: 2 | O9: =SUM(E9:N9) -> 20 | P9: =IF(O9>=17,"Library-ready",IF(O9>=12,"Refine first","Rework")) -> Library-ready | Q9: No deductions.
A10: BB-03-D2 | B10: Business Case Inputs & Strategic Alignment | C10: Deliverable | D10: Business BA | E10: 2 | F10: 2 | G10: 2 | H10: 2 | I10: 2 | J10: 2 | K10: 2 | L10: 2 | M10: 2 | N10: 2 | O10: =SUM(E10:N10) -> 20 | P10: =IF(O10>=17,"Library-ready",IF(O10>=12,"Refine first","Rework")) -> Library-ready | Q10: No deductions.
A11: BB-04-M | B11: Master – Data & Reporting Analysis | C11: Master | D11: Business BA | E11: 2 | F11: 1 | G11: 2 | H11: 2 | I11: 2 | J11: 2 | K11: 2 | L11: 2 | M11: 2 | N11: 2 | O11: =SUM(E11:N11) -> 19 | P11: =IF(O11>=17,"Library-ready",IF(O11>=12,"Refine first","Rework")) -> Library-ready | Q11: Action 1/2: a menu of modes, not one task — deliberate flexibility, but costs single-task clarity. Fix: for repeated use of one mode, use the matching Deliverable prompt instead.
A12: BB-04-D1 | B12: Data Requirements & Dictionary | C12: Deliverable | D12: Business BA | E12: 2 | F12: 2 | G12: 2 | H12: 2 | I12: 2 | J12: 2 | K12: 2 | L12: 2 | M12: 2 | N12: 2 | O12: =SUM(E12:N12) -> 20 | P12: =IF(O12>=17,"Library-ready",IF(O12>=12,"Refine first","Rework")) -> Library-ready | Q12: No deductions.
A13: BB-04-D2 | B13: Reporting Requirements Specification | C13: Deliverable | D13: Business BA | E13: 2 | F13: 2 | G13: 2 | H13: 2 | I13: 2 | J13: 2 | K13: 2 | L13: 2 | M13: 2 | N13: 2 | O13: =SUM(E13:N13) -> 20 | P13: =IF(O13>=17,"Library-ready",IF(O13>=12,"Refine first","Rework")) -> Library-ready | Q13: No deductions.
... A127: PL-07-D2 | B127: AI Adoption Guidelines & Guardrails (Practice) | C127: Deliverable | D127: Practice Lead | E127: 2 | F127: 2 | G127: 2 | H127: 2 | I127: 2 | J127: 2 | K127: 2 | L127: 2 | M127: 2 | N127: 2 | O127: =SUM(E127:N127) -> 20 | P127: =IF(O127>=17,"Library-ready",IF(O127>=12,"Refine first","Rework")) -> Library-ready | Q127: No deductions.
A129: Summary
A130: Prompts scored | B130: =COUNTA(A2:A127) -> 126
A131: Average score | B131: =ROUND(AVERAGE(O2:O127),2) -> 19.67
A132: Minimum / Maximum | B132: =MIN(O2:O127)&" / "&MAX(O2:O127) -> 19 / 20
A133: Library-ready (17–20) | B133: =COUNTIF(P2:P127,"Library-ready") -> 126
A134: At 20/20 | B134: =COUNTIF(O2:O127,20) -> 84
A135: At 19/20 (all Masters) | B135: =COUNTIF(O2:O127,19) -> 42
A137: v0.3 change: the two systematic v0.2 deductions were fixed at the template level — every prompt now carries an in-prompt data-safety rule (C8) and an explicit no-invention/[TBC] convention (C7). The only remaining deduction is C2 on the 42 Masters, which are multi-mode menus by design. Caveat unchanged: the library is designed against this rubric, so paper scores skew high — dry-run, consistency and intern tests on real (de-identified) work remain the stronger evidence.

Sheet Prompt Quality Scorecard
A1: BA Prompt Quality Scorecard — score each criterion 0 (absent), 1 (partial), 2 (met)
A3: Group | B3: Criterion | C3: What good looks like | D3: Scoring anchors | E3: Score (0/1/2)
A4: CARE structure | B4: 1. Context | C4: States who you are (role + organisation) and who the audience for the output is. | D4: 0 = neither; 1 = role or audience only; 2 = both, plus relevant constraints (e.g. privacy, residency).
A5: CARE structure | B5: 2. Action | C5: One clear task with a strong verb; inputs the AI will receive are identified. | D5: 0 = vague ('help me with...'); 1 = clear task but inputs/scope unclear; 2 = clear task, named inputs, explicit scope.
A6: CARE structure | B6: 3. Result / Format | C6: Output structure is specific enough that you could check compliance (sections, table columns, length). | D6: 0 = no format; 1 = loose ('a summary', 'a table'); 2 = exact structure a reviewer could tick off.
A7: CARE structure | B7: 4. Example | C7: Gives a concrete reference point — a sample row, snippet, or 'in the style of' anchor. | D7: 0 = none; 1 = abstract description of an example; 2 = a real, concrete sample the AI can imitate.
A8: BA validation (G.E.T.) | B8: 5. Explain step | C8: Asks the AI to break down the logic used to synthesise the answer. | D8: 0 = absent; 1 = generic 'explain yourself'; 2 = explicit step-by-step reasoning tied to the inputs.
A9: BA validation (G.E.T.) | B9: 6. Test step | C9: Asks for source references, cross-referencing of facts, and a list of assumptions made. | D9: 0 = absent; 1 = sources or assumptions, not both; 2 = sources + cross-reference + assumptions.
A10: BA validation (G.E.T.) | B10: 7. Anti-fabrication | C10: Forbids invented facts/figures; unknowns must be flagged (e.g. [TBC], [PROPOSED — VALIDATE]). | D10: 0 = silent; 1 = implied; 2 = explicit prohibition + a flagging convention.
A11: Safety & reuse | B11: 8. Data safety | C11: Does not require sensitive data; tells the user to de-identify inputs where relevant. | D11: 0 = invites pasting sensitive data; 1 = silent; 2 = explicit de-identification guidance.
A12: Safety & reuse | B12: 9. Reusability | C12: Placeholders are [MARKED]; the prompt works beyond one project or person. | D12: 0 = hard-wired to one case; 1 = partly generic; 2 = fully parameterised with marked placeholders.
A13: Safety & reuse | B13: 10. Right-sized | C13: Every sentence changes the output; nothing is decoration ('would deleting this line change anything?'). | D13: 0 = padded or rambling; 1 = some dead weight; 2 = every element earns its place (long is fine if load-bearing).
D14: TOTAL (max 20) | E14: =SUM(E4:E13) -> 0
D15: Verdict | E15: =IF(COUNT(E4:E13)<10,"—",IF(E14>=17,"Library-ready",IF(E14>=12,"Refine first","Rework"))) -> —
A17: Legend: fill the yellow Score cells (0, 1 or 2). Total and verdict calculate automatically.
A19: Scoring bands
A20: Score | B20: Verdict | C20: Action
A21: 17–20 | B21: Library-ready | C21: Publish to the shared library with version and date.
A22: 12–16 | B22: Usable — refine first | C22: Works for personal use; fix the 0-score criteria before sharing.
A23: 0–11 | B23: Rework | C23: Re-draft against CARE before using — outputs will be unreliable.
A25: Worked example: existing CoPilot 'Level 5 process leveling' prompt — scored 17/20
A26: Criterion | B26: Score | C26: Reasoning
A27: 1. Context | B27: 1 | C27: Says 'I am working on a process flow' — role given loosely; audience for the assessment is never stated.
A28: 2. Action | B28: 2 | C28: Crisp: confirm all elements are Level 5 Tasks against the supplied hierarchy; input (attached diagram) named.
A29: 3. Result / Format | B29: 2 | C29: Exact output table specified: | Process Element | Current Assessment | Appropriate Level | Reasoning | Suggested Revision |.
A30: 4. Example | B30: 2 | C30: The 6-level hierarchy definitions and 'characteristics of a Level 5 Task' give a strong reference point.
A31: 5. Explain step | B31: 2 | C31: Asks how the level assignment was validated and the criteria used for recommendations.
A32: 6. Test step | B32: 2 | C32: Asks for references/frameworks used and inconsistencies, overlaps and gaps found.
A33: 7. Anti-fabrication | B33: 1 | C33: Nothing stops the AI inventing a framework citation; no flagging convention for uncertain assessments.
A34: 8. Data safety | B34: 1 | C34: Silent on whether the attached diagram may contain sensitive operational detail.
A35: 9. Reusability | B35: 2 | C35: Fully generic — works for any Level 5 diagram; nothing project-specific hard-wired.
A36: 10. Right-sized | B36: 2 | C36: Long, but every section (hierarchy, criteria, characteristics, format) is load-bearing.
A37: Total | B37: =SUM(B27:B36) -> 17 | C37: 17/20 → Library-ready. Improve: state the audience; add an anti-fabrication flag; add a de-identification note.

Sheet Delivery Contexts
A1: Delivery Context (L4 sheet) | B1: Catalogue Status | C1: When you're doing this kind of work | D1: BA Services engaged | E1: Prompt IDs to start with | F1: Decomposition gaps flagged
A2: 1. Tech Services (back-end ICT) | B2: Approved | C2: Back-end, non-business-facing ICT projects: platform, integration, observability, security, environments, service readiness. | D2: Environment Access & DevOps Enablement; Integration, Data & Migration; Operational Engineering & Observability; Platform Design & Infrastructure; Security, Privacy & Compliance; Service & Operational Readiness | E2: TB-01-M, TB-01-D1, TB-01-D2, TB-02-M, TB-02-D1, TB-02-D2, TB-03-M, TB-03-D1, TB-03-D2, TB-04-M, TB-04-D1, TB-04-D2, TB-05-M, TB-05-D1, TB-05-D2, TB-06-M, TB-06-D1, TB-06-D2 | F2: None flagged
A3: 2. Procurement – Enablement | B3: Approved | C3: Procuring a new system or services contract: RFI/RFT lifecycle, evaluation, vendor selection. | D3: Commercial, Licencing & Vendor Mgmt; Business Project Discovery & Problem Definition; Business Needs Assessments (Initial and High Level Requirements); Process Analysis & Improvement; Functional Requirements Analysis & Refinement; Solution Analysis & Design Support; Stakeholder Analysis & Engagement; Requirements Governance & Traceability; Sizing, Estimation, Dependency and Prioritisation Management; Operational Readiness & Transition; Benefits Realisation & KPI Management; Testing & Requirements Validation Support | E3: BT-03-M, BT-03-D1, BT-03-D2, BB-03-M, BB-03-D1, BB-03-D2, BB-02-M, BB-02-D1, BB-02-D2, BB-07-M, BB-07-D1, BB-07-D2, BB-06-M, BB-06-D1, BB-06-D2, BT-07-M, BT-07-D1, BT-07-D2, BT-08-M, BT-08-D1, BT-08-D2, BT-05-M, BT-05-D1, BT-05-D2, BT-06-M, BT-06-D1, BT-06-D2, BT-04-M, BT-04-D1, BT-04-D2, BB-01-M, BB-01-D1, BB-01-D2, BT-09-M, BT-09-D1, BT-09-D2 | F3: GAP: procuring AI products/services (AI assurance criteria in RFT) not yet decomposed
A4: 3. IT System – Update | B4: Approved | C4: Updating functions, features or reports in an existing business-facing system. | D4: Defect & Work-around Analysis; Business Needs Assessments (Initial and High Level Requirements); Functional Requirements Analysis & Refinement; Process Analysis & Improvement; Sizing, Estimation, Dependency and Prioritisation Management; Testing & Requirements Validation Support; Operational Readiness & Transition; Requirements Governance & Traceability | E4: BB-05-M, BB-05-D1, BB-05-D2, BB-02-M, BB-02-D1, BB-02-D2, BB-06-M, BB-06-D1, BB-06-D2, BB-07-M, BB-07-D1, BB-07-D2, BT-06-M, BT-06-D1, BT-06-D2, BT-09-M, BT-09-D1, BT-09-D2, BT-04-M, BT-04-D1, BT-04-D2, BT-05-M, BT-05-D1, BT-05-D2 | F4: GAP: stakeholder engagement for system updates not yet decomposed
A5: 4. IT System – Agile | B5: Approved | C5: Business-facing technology delivery on an agile cadence. | D5: Backlog Management (Agile); Agile Ceremony Facilitation & Support; User Story Mapping & Slicing; Just-in-Time Requirements Elaboration; Iteration & Release Planning Support; Agile Metrics & Flow Analysis; Agile Ways of Working Uplift | E5: BT-02-M, BT-02-D1, BT-02-D2, AB-01-M, AB-01-D1, AB-01-D2, AB-02-M, AB-02-D1, AB-02-D2, AB-03-M, AB-03-D1, AB-03-D2, AB-04-M, AB-04-D1, AB-04-D2, AB-05-M, AB-05-D1, AB-05-D2, AB-06-M, AB-06-D1, AB-06-D2 | F5: GAPs: story sizing & estimation; agile testing & validation support not yet decomposed
A6: 5. IT System – New / Transition | B6: Approved | C6: Transitioning services to a new system, introducing a new system, or digitising a manual process. | D6: Business Project Discovery & Problem Definition; Business Needs Assessments (Initial and High Level Requirements); Process Analysis & Improvement; Functional Requirements Analysis & Refinement; Solution Analysis & Design Support; Integration, Data & Migration; Operational Readiness & Transition; Testing & Requirements Validation Support; Stakeholder Analysis & Engagement; Benefits Realisation & KPI Management | E6: BB-03-M, BB-03-D1, BB-03-D2, BB-02-M, BB-02-D1, BB-02-D2, BB-07-M, BB-07-D1, BB-07-D2, BB-06-M, BB-06-D1, BB-06-D2, BT-07-M, BT-07-D1, BT-07-D2, TB-02-M, TB-02-D1, TB-02-D2, BT-04-M, BT-04-D1, BT-04-D2, BT-09-M, BT-09-D1, BT-09-D2, BT-08-M, BT-08-D1, BT-08-D2, BB-01-M, BB-01-D1, BB-01-D2 | F6: None flagged
A7: 6. Process – Design | B7: Approved | C7: Re-engineering business processes for new or transformed outcomes or regulatory needs; includes process levelling (L1-L6 hierarchy) validation. | D7: Business Project Discovery & Problem Definition; Process Analysis & Improvement; Business Needs Assessments (Initial and High Level Requirements); Stakeholder Analysis & Engagement; Benefits Realisation & KPI Management; Operational Readiness & Transition | E7: BB-03-M, BB-03-D1, BB-03-D2, BB-07-M, BB-07-D1, BB-07-D2, BB-02-M, BB-02-D1, BB-02-D2, BT-08-M, BT-08-D1, BT-08-D2, BB-01-M, BB-01-D1, BB-01-D2, BT-04-M, BT-04-D1, BT-04-D2 | F7: None flagged
A8: 7. Process – Improvement | B8: Approved | C8: Assessing and modifying existing processes to rectify risks or improve service outcomes. | D8: Process Analysis & Improvement; Defect & Work-around Analysis; Benefits Realisation & KPI Management; Stakeholder Analysis & Engagement | E8: BB-07-M, BB-07-D1, BB-07-D2, BB-05-M, BB-05-D1, BB-05-D2, BB-01-M, BB-01-D1, BB-01-D2, BT-08-M, BT-08-D1, BT-08-D2 | F8: None flagged
A9: 8. Consultancy | B9: Approved | C9: Business consultancy: capability assessment/audit, decision support, strategic costing, organisational impact, strategic alignment, business architecture. | D9: Strategic Business Analysis & Advisory; Business Project Discovery & Problem Definition | E9: BB-08-M, BB-08-D1, BB-08-D2, BB-03-M, BB-03-D1, BB-03-D2 | F9: None flagged
A10: 9. Data – Warehouse | B10: Approved | C10: Data management projects across the medallion Bronze/Silver/Gold layers: business questions, BI specs, layer mapping, legacy analytics platform transition. | D10: Data & Reporting Analysis; Integration, Data & Migration; Testing & Requirements Validation Support; Stakeholder Analysis & Engagement | E10: BB-04-M, BB-04-D1, BB-04-D2, TB-02-M, TB-02-D1, TB-02-D2, BT-09-M, BT-09-D1, BT-09-D2, BT-08-M, BT-08-D1, BT-08-D2 | F10: GAP: governance & traceability of BI requirements not yet decomposed
A11: 10. AI – Agentic | B11: Approved | C11: Solutions delivered on agentic AI platforms: use case & assurance, agent behaviour, grounding/RAG, responsible AI, consumption controls, sustainability. | D11: AI Transformation; Security, Privacy & Compliance; Commercial, Licencing & Vendor Mgmt; Service & Operational Readiness; Benefits Realisation & KPI Management; Solution Analysis & Design Support | E11: BT-01-M, BT-01-D1, BT-01-D2, TB-05-M, TB-05-D1, TB-05-D2, BT-03-M, BT-03-D1, BT-03-D2, TB-06-M, TB-06-D1, TB-06-D2, BB-01-M, BB-01-D1, BB-01-D2, BT-07-M, BT-07-D1, BT-07-D2 | F11: GAPs: traceability of agent requirements & decisions; agent evaluation & testing support not yet decomposed
A12: 11. Leadership | B12: Approved | C12: Lead BA and Practice Lead services: planning, leading, assuring and uplifting BA delivery. | D12: BA Engagement Planning & Estimation; BA Team Leadership & Work Allocation; Requirements Quality Assurance & Review; Cross-Stream Scope & Dependency Coordination; Senior Stakeholder & Sponsor Engagement; BA Mentoring & Capability Development; BA Practice Strategy & Operating Model; Standards, Methods & Templates; Capability & Competency Management; Workforce & Resource Management; Practice Performance & Continuous Improvement; Community of Practice & Knowledge Management; Tooling & AI Enablement | E12: LB-01-M, LB-01-D1, LB-01-D2, LB-02-M, LB-02-D1, LB-02-D2, LB-03-M, LB-03-D1, LB-03-D2, LB-04-M, LB-04-D1, LB-04-D2, LB-05-M, LB-05-D1, LB-05-D2, LB-06-M, LB-06-D1, LB-06-D2, PL-01-M, PL-01-D1, PL-01-D2, PL-02-M, PL-02-D1, PL-02-D2, PL-03-M, PL-03-D1, PL-03-D2, PL-04-M, PL-04-D1, PL-04-D2, PL-05-M, PL-05-D1, PL-05-D2, PL-06-M, PL-06-D1, PL-06-D2, PL-07-M, PL-07-D1, PL-07-D2 | F12: None flagged
